nprimos/nprimos.py
nprimosLeonorPriego-1.2.dist-info/LICENSE.txt
nprimosLeonorPriego-1.2.dist-info/METADATA
nprimosLeonorPriego-1.2.dist-info/WHEEL
nprimosLeonorPriego-1.2.dist-info/top_level.txt
nprimosLeonorPriego-1.2.dist-info/RECORD
