Metadata-Version: 2.1
Name: nprimosLeonorPriego
Version: 1.2
Summary: Print all prime numbers between 1 and MaxNum, you have to indicate maxNum.
License-File: LICENSE.txt
